{"estados": {"1": {"cpu_usage": 7.6, "memory_usage": 5.4, "disk_free": 947.58, "timestamp": "2025-04-23T21:11:32.363457"}, "2": {"cpu_usage": 1.0, "memory_usage": 5.4, "disk_free": 947.58, "timestamp": "2025-04-23T21:11:32.877144"}, "3": {"cpu_usage": 0.1, "memory_usage": 5.4, "disk_free": 947.58, "timestamp": "2025-04-23T21:11:38.886421"}, "4": {"cpu_usage": 0.2, "memory_usage": 5.4, "disk_free": 947.58, "timestamp": "2025-04-23T21:11:44.903849"}, "5": {"cpu_usage": 0.1, "memory_usage": 5.4, "disk_free": 947.58, "timestamp": "2025-04-23T21:11:50.910016"}, "6": {"cpu_usage": 1.2, "memory_usage": 5.4, "disk_free": 947.58, "timestamp": "2025-04-23T21:11:56.922153"}, "7": {"cpu_usage": 0.1, "memory_usage": 5.4, "disk_free": 947.58, "timestamp": "2025-04-23T21:12:02.929155"}, "8": {"cpu_usage": 0.1, "memory_usage": 5.4, "disk_free": 947.58, "timestamp": "2025-04-23T21:12:08.943534"}, "9": {"cpu_usage": 0.4, "memory_usage": 5.5, "disk_free": 947.58, "timestamp": "2025-04-23T21:12:14.951288"}, "10": {"cpu_usage": 0.0, "memory_usage": 5.5, "disk_free": 947.58, "timestamp": "2025-04-23T21:12:20.958214"}}}